bandersnatch/__init__.py
bandersnatch/__main__.py
bandersnatch/configuration.py
bandersnatch/defaults.conf
bandersnatch/delete.py
bandersnatch/errors.py
bandersnatch/example.conf
bandersnatch/filter.py
bandersnatch/log.py
bandersnatch/main.py
bandersnatch/master.py
bandersnatch/mirror.py
bandersnatch/package.py
bandersnatch/simple.py
bandersnatch/storage.py
bandersnatch/unittest.conf
bandersnatch/utils.py
bandersnatch/verify.py
bandersnatch/config/__init__.py
bandersnatch/config/diff_file_reference.py
bandersnatch/config/exceptions.py
bandersnatch/config/proxy.py
bandersnatch/tests/__init__.py
bandersnatch/tests/conftest.py
bandersnatch/tests/mock_config.py
bandersnatch/tests/test_configuration.py
bandersnatch/tests/test_delete.py
bandersnatch/tests/test_filter.py
bandersnatch/tests/test_main.py
bandersnatch/tests/test_master.py
bandersnatch/tests/test_mirror.py
bandersnatch/tests/test_package.py
bandersnatch/tests/test_proxy_config.py
bandersnatch/tests/test_simple.py
bandersnatch/tests/test_simple_fixtures.py
bandersnatch/tests/test_sync.py
bandersnatch/tests/test_utils.py
bandersnatch/tests/test_verify.py
bandersnatch-7.0.1.dist-info/licenses/LICENSE
bandersnatch_filter_plugins/__init__.py
bandersnatch_filter_plugins/allowlist_name.py
bandersnatch_filter_plugins/blocklist_name.py
bandersnatch_filter_plugins/encoding.py
bandersnatch_filter_plugins/filename_name.py
bandersnatch_filter_plugins/latest_name.py
bandersnatch_filter_plugins/metadata_filter.py
bandersnatch_filter_plugins/prerelease_name.py
bandersnatch_filter_plugins/regex_name.py
bandersnatch_storage_plugins/__init__.py
bandersnatch_storage_plugins/filesystem.py
bandersnatch_storage_plugins/s3.py
bandersnatch-7.0.1.dist-info/METADATA
bandersnatch-7.0.1.dist-info/WHEEL
bandersnatch-7.0.1.dist-info/entry_points.txt
bandersnatch-7.0.1.dist-info/top_level.txt
bandersnatch-7.0.1.dist-info/RECORD
