Metadata-Version: 2.4
Name: bandersnatch
Version: 7.0.1
Summary: Mirroring tool that implements the client (mirror) side of PEP 381
Home-page: https://github.com/pypa/bandersnatch/
Author: Christian Theune
Author-email: ct@flyingcircus.io
License: Academic Free License, version 3
Project-URL: Source Code, https://github.com/pypa/bandersnatch
Project-URL: Change Log, https://github.com/pypa/bandersnatch/blob/master/CHANGES.md
Classifier: Programming Language :: Python :: 3 :: Only
Classifier: Programming Language :: Python :: 3.12
Classifier: Programming Language :: Python :: 3.13
Classifier: Programming Language :: Python :: 3.14
Requires-Python: >=3.12
License-File: LICENSE
Requires-Dist: aiohttp
Requires-Dist: aiohttp-socks
Requires-Dist: aiohttp-xmlrpc
Requires-Dist: filelock
Requires-Dist: humanfriendly
Requires-Dist: packaging
Requires-Dist: setuptools
Provides-Extra: safety-db
Requires-Dist: bandersnatch_safety_db; extra == "safety-db"
Provides-Extra: uvloop
Requires-Dist: uvloop; extra == "uvloop"
Provides-Extra: s3
Requires-Dist: s3path>=0.5.5; extra == "s3"
Dynamic: license-file
